sequana_pipelines/revcomp/__init__.py
sequana_pipelines/revcomp/config.yaml
sequana_pipelines/revcomp/main.py
sequana_pipelines/revcomp/revcomp.rules
sequana_pipelines/revcomp/schema.yaml
sequana_pipelines/revcomp/tools.txt
sequana_revcomp-1.1.0.dist-info/LICENSE
sequana_revcomp-1.1.0.dist-info/METADATA
sequana_revcomp-1.1.0.dist-info/WHEEL
sequana_revcomp-1.1.0.dist-info/entry_points.txt
sequana_revcomp-1.1.0.dist-info/RECORD
