Metadata-Version: 2.1
Name: sequana-revcomp
Version: 1.1.0
Summary: reverse complement a set of FastQ files
Home-page: https://github.com/sequana/revcomp
License: BSD-3
Keywords: snakemake,NGS,sequana,bwa,minimap2
Author: Sequana Team
Requires-Python: >=3.8,<4.0
Classifier: Development Status :: 5 - Production/Stable
Classifier: Intended Audience :: Developers
Classifier: Intended Audience :: Education
Classifier: Intended Audience :: End Users/Desktop
Classifier: Intended Audience :: Science/Research
Classifier: License :: OSI Approved :: BSD License
Classifier: License :: Other/Proprietary License
Classifier: Operating System :: POSIX :: Linux
Classifier: Programming Language :: Python :: 3
Classifier: Programming Language :: Python :: 3.8
Classifier: Programming Language :: Python :: 3.9
Classifier: Programming Language :: Python :: 3.10
Classifier: Programming Language :: Python :: 3.11
Classifier: Programming Language :: Python :: 3.10
Classifier: Programming Language :: Python :: 3.8
Classifier: Programming Language :: Python :: 3.9
Classifier: Topic :: Scientific/Engineering :: Bio-Informatics
Classifier: Topic :: Scientific/Engineering :: Information Analysis
Classifier: Topic :: Software Development :: Libraries :: Python Modules
Requires-Dist: click (>=8.1.7,<9.0.0)
Requires-Dist: click-completion (>=0.5.2,<0.6.0)
Requires-Dist: rich-click (>=1.7.2,<2.0.0)
Requires-Dist: sequana (>=0.16.4)
Requires-Dist: sequana_pipetools (>=0.16.6)
Project-URL: Repository, https://github.com/sequana/revcomp
